[{"name":"number 6","hebName":"aw","size":"why","file":"IMG_7443.jpg"},{"name":"i","hebName":"","size":"","file":"IMG_7444.jpg"},{"file":"IMG_7457.jpg"},{"file":"IMG_7460.jpg"},{"file":"IMG_7478.jpg"},{"file":"IMG_7497.jpg"},{"file":"IMG_7562.jpg"},{"file":"IMG_7603.jpg"},{"file":"IMG_7653.jpg"},{"file":"IMG_7393.jpg"},{"file":"IMG_7389.jpg"},{"file":"IMG_7388.jpg"},{"file":"IMG_7360.jpg"},{"file":"IMG_7353.jpg"},{"file":"IMG_7294.jpg"},{"file":"IMG_7290.jpg"},{"file":"IMG_6856.jpg"},{"file":"IMG_6849.jpg"},{"file":"IMG_6759.jpg"},{"file":"IMG_6735.jpg"},{"file":"IMG_6043.jpg"},{"file":"IMG_5299.jpg"},{"file":"IMG_5298.jpg"},{"file":"IMG_5244.jpg"},{"file":"IMG_5219.jpg"},{"file":"IMG_4766.jpg"},{"file":"IMG_4719.jpg"},{"file":"IMG_4661.jpg"},{"file":"IMG_4585.jpg"},{"file":"IMG_4514.jpg"},{"file":"IMG_4492.jpg"},{"file":"IMG_4485.jpg"},{"file":"IMG_4439.jpg"},{"file":"IMG_4352.jpg"},{"file":"IMG_4351.jpg"},{"file":"IMG_4335.jpg"},{"file":"IMG_4324.jpg"},{"file":"IMG_4300.jpg"},{"file":"IMG_4274.jpg"},{"file":"IMG_4237.jpg"},{"file":"IMG_4236.jpg"},{"file":"IMG_4221.jpg"},{"file":"IMG_4206.jpg"},{"file":"IMG_4133.jpg"},{"file":"IMG_4010.jpg"},{"file":"IMG_4007.jpg"},{"file":"IMG_7399.jpg"}]